add_time/__init__.py
add_time/api.py
add_time/application.py
add_time/get_event.py
add_time/handler.py
add_time/sample_events.py
add_time/controllers/add_time_controller.py
add_time/controllers/base_controller.py
add_time/factories/base_factory.py
add_time/factories/factory.py
add_time/infra/add_time.py
add_time/infra/script.py
add_time/models/request.py
add_time/models/response.py
add_time/services/add_time_service.py
add_time/services/base_service.py
add_time/utils/audio.py
add_time/utils/file.py
add_time/utils/helpers.py
add_time/utils/html.py
add_time/utils/json.py
add_time/utils/lambda_helpers.py
add_time/utils/markdown.py
add_time/utils/object_factory.py
add_time/utils/source.py
add_time/utils/string_utils.py
add_time/utils/text.py
add_time/utils/time.py
add_time/utils/url.py
video_bot_add_time-0.0.5.dist-info/LICENSE
video_bot_add_time-0.0.5.dist-info/METADATA
video_bot_add_time-0.0.5.dist-info/WHEEL
video_bot_add_time-0.0.5.dist-info/top_level.txt
video_bot_add_time-0.0.5.dist-info/RECORD
