Metadata-Version: 2.1
Name: video-bot-add-time
Version: 0.0.5
Summary: Add Times module
Author-email: Bruno de Paula <bruno.bert.jj@gmail.com>
License: MIT License
Project-URL: Homepage, https://github.com/bruno-bert/microservice-add-time
Keywords: audio,readtime
Classifier: Programming Language :: Python :: 3
Classifier: License :: OSI Approved :: MIT License
Classifier: Operating System :: OS Independent
Requires-Python: >=3.7
License-File: LICENSE
Requires-Dist: aniso8601 (==9.0.1)
Requires-Dist: beautifulsoup4 (==4.11.1)
Requires-Dist: click (==8.1.3)
Requires-Dist: coloredlogs (==15.0.1)
Requires-Dist: cssselect (==1.2.0)
Requires-Dist: Flask (==2.2.2)
Requires-Dist: Flask-RESTful (==0.3.9)
Requires-Dist: humanfriendly (==10.0)
Requires-Dist: importlib-metadata (==5.2.0)
Requires-Dist: itsdangerous (==2.1.2)
Requires-Dist: Jinja2 (==3.1.2)
Requires-Dist: lxml (==4.9.2)
Requires-Dist: markdown2 (==2.4.6)
Requires-Dist: MarkupSafe (==2.1.1)
Requires-Dist: mutagen (==1.46.0)
Requires-Dist: pyquery (==1.4.3)
Requires-Dist: python-dotenv (==0.21.0)
Requires-Dist: pytz (==2022.7)
Requires-Dist: readtime (==2.0.0)
Requires-Dist: six (==1.16.0)
Requires-Dist: soupsieve (==2.3.2.post1)
Requires-Dist: typing-extensions (==4.4.0)
Requires-Dist: Werkzeug (==2.2.2)
Requires-Dist: zipp (==3.11.0)
